met/__init__.py
met/location.py
met/metportal.py
met/metvariable.py
met/observations.py
met/package_info.py
met/wave.py
met/wind.py
met/blueprints/__init__.py
met/blueprints/location.py
met/blueprints/metportal.py
met/blueprints/metvariable.py
met/blueprints/observations.py
met/blueprints/wave.py
met/blueprints/wind.py
met/jobs/__init__.py
met/jobs/job.py
met/jobs/jobresult.py
met/jobs/jobrunner.py
met/jobs/blueprints/__init__.py
met/jobs/blueprints/job.py
met/jobs/blueprints/jobresult.py
met/jobs/blueprints/jobrunner.py
met/nora3/__init__.py
met/nora3/field.py
met/nora3/fieldpoint.py
met/nora3/windarea.py
met/nora3/blueprints/__init__.py
met/nora3/blueprints/field.py
met/nora3/blueprints/fieldpoint.py
met/nora3/blueprints/windarea.py
met/scatter/__init__.py
met/scatter/scatter.py
met/scatter/sector.py
met/scatter/wave.py
met/scatter/windcurrent.py
met/scatter/blueprints/__init__.py
met/scatter/blueprints/scatter.py
met/scatter/blueprints/sector.py
met/scatter/blueprints/wave.py
met/scatter/blueprints/windcurrent.py
metlib/__init__.py
metlib/catalog.py
metlib/create_location_entities.py
metlib/jsonencoder.py
metlib/latlon.py
metlib/scatter.py
dmtmetlib-0.0.4.dev0.dist-info/METADATA
dmtmetlib-0.0.4.dev0.dist-info/WHEEL
dmtmetlib-0.0.4.dev0.dist-info/top_level.txt
dmtmetlib-0.0.4.dev0.dist-info/RECORD
